camsai/__init__.py
camsai/notebooks/__init__.py
camsai/notebooks/utils/__init__.py
camsai_notebooks-2024.12.13.post0.dist-info/METADATA
camsai_notebooks-2024.12.13.post0.dist-info/WHEEL
camsai_notebooks-2024.12.13.post0.dist-info/top_level.txt
camsai_notebooks-2024.12.13.post0.dist-info/RECORD
